odoo8_addon_stock_picking_show_return-8.0.1.0.0.99.dev13-nspkg.pth
odoo_addons/stock_picking_show_return/README.rst
odoo_addons/stock_picking_show_return/__init__.py
odoo_addons/stock_picking_show_return/__openerp__.py
odoo_addons/stock_picking_show_return/i18n/de.po
odoo_addons/stock_picking_show_return/i18n/es.po
odoo_addons/stock_picking_show_return/i18n/es_AR.po
odoo_addons/stock_picking_show_return/i18n/fi.po
odoo_addons/stock_picking_show_return/i18n/fr.po
odoo_addons/stock_picking_show_return/i18n/it.po
odoo_addons/stock_picking_show_return/i18n/pt_BR.po
odoo_addons/stock_picking_show_return/i18n/sl.po
odoo_addons/stock_picking_show_return/i18n/stock_picking_show_return.pot
odoo_addons/stock_picking_show_return/i18n/tr.po
odoo_addons/stock_picking_show_return/i18n/tr_TR.po
odoo_addons/stock_picking_show_return/models/__init__.py
odoo_addons/stock_picking_show_return/models/stock_picking.py
odoo_addons/stock_picking_show_return/static/description/icon.png
odoo_addons/stock_picking_show_return/tests/__init__.py
odoo_addons/stock_picking_show_return/tests/test_stock_picking_show_return.py
odoo_addons/stock_picking_show_return/views/stock_picking_view.xml
odoo8_addon_stock_picking_show_return-8.0.1.0.0.99.dev13.dist-info/METADATA
odoo8_addon_stock_picking_show_return-8.0.1.0.0.99.dev13.dist-info/WHEEL
odoo8_addon_stock_picking_show_return-8.0.1.0.0.99.dev13.dist-info/namespace_packages.txt
odoo8_addon_stock_picking_show_return-8.0.1.0.0.99.dev13.dist-info/top_level.txt
odoo8_addon_stock_picking_show_return-8.0.1.0.0.99.dev13.dist-info/RECORD
